{"test_class": {"identifier": "DefaultMatchCountImplTest", "superclass": "", "interfaces": "", "fields": [{"original_string": "private static final String ID_LABEL = \"id\";", "modifier": "private static final", "type": "String", "declarator": "ID_LABEL = \"id\"", "var_name": "ID_LABEL"}, {"original_string": "private static final String NAME_LABEL = \"label\";", "modifier": "private static final", "type": "String", "declarator": "NAME_LABEL = \"label\"", "var_name": "NAME_LABEL"}, {"original_string": "private static final String COUNT_LABEL = \"count\";", "modifier": "private static final", "type": "String", "declarator": "COUNT_LABEL = \"count\"", "var_name": "COUNT_LABEL"}, {"original_string": "private static final String GENE_1 = \"gene1\";", "modifier": "private static final", "type": "String", "declarator": "GENE_1 = \"gene1\"", "var_name": "GENE_1"}, {"original_string": "private static final String GENE_1_SYNONYM = \"gene1_synonym\";", "modifier": "private static final", "type": "String", "declarator": "GENE_1_SYNONYM = \"gene1_synonym\"", "var_name": "GENE_1_SYNONYM"}, {"original_string": "private static final String GENE_2 = \"gene2\";", "modifier": "private static final", "type": "String", "declarator": "GENE_2 = \"gene2\"", "var_name": "GENE_2"}, {"original_string": "private static final String GENE_3 = \"gene3\";", "modifier": "private static final", "type": "String", "declarator": "GENE_3 = \"gene3\"", "var_name": "GENE_3"}, {"original_string": "private static final String HP01 = \"HP:01\";", "modifier": "private static final", "type": "String", "declarator": "HP01 = \"HP:01\"", "var_name": "HP01"}, {"original_string": "private static final String HP01_NAME = \"Phenotype 01\";", "modifier": "private static final", "type": "String", "declarator": "HP01_NAME = \"Phenotype 01\"", "var_name": "HP01_NAME"}, {"original_string": "private static final String HP02 = \"HP:02\";", "modifier": "private static final", "type": "String", "declarator": "HP02 = \"HP:02\"", "var_name": "HP02"}, {"original_string": "private static final String HP02_NAME = \"Phenotype 02\";", "modifier": "private static final", "type": "String", "declarator": "HP02_NAME = \"Phenotype 02\"", "var_name": "HP02_NAME"}, {"original_string": "private static final Collection<String> HP01_GENES = Arrays.asList(GENE_1, null, GENE_1_SYNONYM, GENE_2, GENE_3);", "modifier": "private static final", "type": "Collection<String>", "declarator": "HP01_GENES = Arrays.asList(GENE_1, null, GENE_1_SYNONYM, GENE_2, GENE_3)", "var_name": "HP01_GENES"}, {"original_string": "@Mock\n    private VocabularyTerm feature1;", "modifier": "@Mock\n    private", "type": "VocabularyTerm", "declarator": "feature1", "var_name": "feature1"}, {"original_string": "@Mock\n    private VocabularyTerm feature2;", "modifier": "@Mock\n    private", "type": "VocabularyTerm", "declarator": "feature2", "var_name": "feature2"}, {"original_string": "private MatchCount component;", "modifier": "private", "type": "MatchCount", "declarator": "component", "var_name": "component"}, {"original_string": "private MatchCount noGenesComponent;", "modifier": "private", "type": "MatchCount", "declarator": "noGenesComponent", "var_name": "noGenesComponent"}], "file": "components/gene-panels/api/src/test/java/org/phenotips/panels/internal/DefaultMatchCountImplTest.java"}, "test_case": {"identifier": "getNameIsNull", "parameters": "()", "modifiers": "@Test public", "return": "void", "body": "@Test\n    public void getNameIsNull()\n    {\n        when(this.feature1.getTranslatedName()).thenReturn(null);\n        Assert.assertNull(this.component.getName());\n    }", "signature": "void getNameIsNull()", "full_signature": "@Test public void getNameIsNull()", "class_method_signature": "DefaultMatchCountImplTest.getNameIsNull()", "testcase": true, "constructor": false, "invocations": ["thenReturn", "when", "getTranslatedName", "assertNull", "getName"]}, "focal_class": {"identifier": "DefaultMatchCountImpl", "superclass": "", "interfaces": "implements MatchCount", "fields": [{"original_string": "private static final String NULL_TERM_ERROR_MSG = \"The vocabulary term must not be null\";", "modifier": "private static final", "type": "String", "declarator": "NULL_TERM_ERROR_MSG = \"The vocabulary term must not be null\"", "var_name": "NULL_TERM_ERROR_MSG"}, {"original_string": "private static final String ID_LABEL = \"id\";", "modifier": "private static final", "type": "String", "declarator": "ID_LABEL = \"id\"", "var_name": "ID_LABEL"}, {"original_string": "private static final String NAME_LABEL = \"label\";", "modifier": "private static final", "type": "String", "declarator": "NAME_LABEL = \"label\"", "var_name": "NAME_LABEL"}, {"original_string": "private static final String COUNT_LABEL = \"count\";", "modifier": "private static final", "type": "String", "declarator": "COUNT_LABEL = \"count\"", "var_name": "COUNT_LABEL"}, {"original_string": "private final VocabularyTerm term;", "modifier": "private final", "type": "VocabularyTerm", "declarator": "term", "var_name": "term"}, {"original_string": "private final List<String> genes;", "modifier": "private final", "type": "List<String>", "declarator": "genes", "var_name": "genes"}], "methods": [{"identifier": "DefaultMatchCountImpl", "parameters": "(@Nonnull final VocabularyTerm term, @Nullable final Collection<String> associatedGenes)", "modifiers": "", "return": "", "signature": " DefaultMatchCountImpl(@Nonnull final VocabularyTerm term, @Nullable final Collection<String> associatedGenes)", "full_signature": "  DefaultMatchCountImpl(@Nonnull final VocabularyTerm term, @Nullable final Collection<String> associatedGenes)", "class_method_signature": "DefaultMatchCountImpl.DefaultMatchCountImpl(@Nonnull final VocabularyTerm term, @Nullable final Collection<String> associatedGenes)", "testcase": false, "constructor": true}, {"identifier": "getCount", "parameters": "()", "modifiers": "@Override public", "return": "int", "signature": "int getCount()", "full_signature": "@Override public int getCount()", "class_method_signature": "DefaultMatchCountImpl.getCount()", "testcase": false, "constructor": false}, {"identifier": "getId", "parameters": "()", "modifiers": "@Override public", "return": "String", "signature": "String getId()", "full_signature": "@Override public String getId()", "class_method_signature": "DefaultMatchCountImpl.getId()", "testcase": false, "constructor": false}, {"identifier": "getName", "parameters": "()", "modifiers": "@Override public", "return": "String", "signature": "String getName()", "full_signature": "@Override public String getName()", "class_method_signature": "DefaultMatchCountImpl.getName()", "testcase": false, "constructor": false}, {"identifier": "getGenes", "parameters": "()", "modifiers": "@Override public", "return": "Collection<String>", "signature": "Collection<String> getGenes()", "full_signature": "@Override public Collection<String> getGenes()", "class_method_signature": "DefaultMatchCountImpl.getGenes()", "testcase": false, "constructor": false}, {"identifier": "toJSON", "parameters": "()", "modifiers": "@Override public", "return": "JSONObject", "signature": "JSONObject toJSON()", "full_signature": "@Override public JSONObject toJSON()", "class_method_signature": "DefaultMatchCountImpl.toJSON()", "testcase": false, "constructor": false}, {"identifier": "equals", "parameters": "(@Nullable final Object o)", "modifiers": "@Override public", "return": "boolean", "signature": "boolean equals(@Nullable final Object o)", "full_signature": "@Override public boolean equals(@Nullable final Object o)", "class_method_signature": "DefaultMatchCountImpl.equals(@Nullable final Object o)", "testcase": false, "constructor": false}, {"identifier": "hashCode", "parameters": "()", "modifiers": "@Override public", "return": "int", "signature": "int hashCode()", "full_signature": "@Override public int hashCode()", "class_method_signature": "DefaultMatchCountImpl.hashCode()", "testcase": false, "constructor": false}, {"identifier": "compareTo", "parameters": "(@Nonnull final MatchCount o)", "modifiers": "@Override public", "return": "int", "signature": "int compareTo(@Nonnull final MatchCount o)", "full_signature": "@Override public int compareTo(@Nonnull final MatchCount o)", "class_method_signature": "DefaultMatchCountImpl.compareTo(@Nonnull final MatchCount o)", "testcase": false, "constructor": false}], "file": "components/gene-panels/api/src/main/java/org/phenotips/panels/internal/DefaultMatchCountImpl.java"}, "focal_method": {"identifier": "getName", "parameters": "()", "modifiers": "@Override public", "return": "String", "body": "@Override\n    public String getName()\n    {\n        return this.term.getTranslatedName();\n    }", "signature": "String getName()", "full_signature": "@Override public String getName()", "class_method_signature": "DefaultMatchCountImpl.getName()", "testcase": false, "constructor": false, "invocations": ["getTranslatedName"]}, "repository": {"repo_id": 2685841, "url": "https://github.com/phenotips/phenotips", "language": "Java", "is_fork": false, "fork_count": 64, "stargazer_count": 87, "size": 1662205, "license": "licensed"}}