{"test_class": {"identifier": "AutoStopTest", "superclass": "", "interfaces": "", "fields": [], "file": "plugins/autostop/src/test/java/kg/apc/jmeter/reporters/AutoStopTest.java"}, "test_case": {"identifier": "testSetErrorRate", "parameters": "()", "modifiers": "@Test public", "return": "void", "body": "@Test\n    public void testSetErrorRate() {\n        System.out.println(\"setErrorRate\");\n        String text = \"\";\n        AutoStop instance = new AutoStop();\n        instance.setErrorRate(text);\n    }", "signature": "void testSetErrorRate()", "full_signature": "@Test public void testSetErrorRate()", "class_method_signature": "AutoStopTest.testSetErrorRate()", "testcase": true, "constructor": false, "invocations": ["println", "setErrorRate"]}, "focal_class": {"identifier": "AutoStop", "superclass": "extends AbstractListenerElement", "interfaces": "implements SampleListener, Serializable,\n        TestStateListener, Remoteable, NoThreadClone", "fields": [{"original_string": "private static final Logger log = LoggingManager.getLoggerForClass();", "modifier": "private static final", "type": "Logger", "declarator": "log = LoggingManager.getLoggerForClass()", "var_name": "log"}, {"original_string": "private final static String RESPONSE_TIME = \"avg_response_time\";", "modifier": "private final static", "type": "String", "declarator": "RESPONSE_TIME = \"avg_response_time\"", "var_name": "RESPONSE_TIME"}, {"original_string": "private final static String ERROR_RATE = \"error_rate\";", "modifier": "private final static", "type": "String", "declarator": "ERROR_RATE = \"error_rate\"", "var_name": "ERROR_RATE"}, {"original_string": "private final static String RESPONSE_TIME_SECS = \"avg_response_time_length\";", "modifier": "private final static", "type": "String", "declarator": "RESPONSE_TIME_SECS = \"avg_response_time_length\"", "var_name": "RESPONSE_TIME_SECS"}, {"original_string": "private final static String ERROR_RATE_SECS = \"error_rate_length\";", "modifier": "private final static", "type": "String", "declarator": "ERROR_RATE_SECS = \"error_rate_length\"", "var_name": "ERROR_RATE_SECS"}, {"original_string": "private final static String RESPONSE_LATENCY = \"avg_response_latency\";", "modifier": "private final static", "type": "String", "declarator": "RESPONSE_LATENCY = \"avg_response_latency\"", "var_name": "RESPONSE_LATENCY"}, {"original_string": "private final static String RESPONSE_LATENCY_SECS = \"avg_response_latency_length\";", "modifier": "private final static", "type": "String", "declarator": "RESPONSE_LATENCY_SECS = \"avg_response_latency_length\"", "var_name": "RESPONSE_LATENCY_SECS"}, {"original_string": "private long curSec = 0L;", "modifier": "private", "type": "long", "declarator": "curSec = 0L", "var_name": "curSec"}, {"original_string": "private GraphPanelChartAverageElement avgRespTime = new GraphPanelChartAverageElement();", "modifier": "private", "type": "GraphPanelChartAverageElement", "declarator": "avgRespTime = new GraphPanelChartAverageElement()", "var_name": "avgRespTime"}, {"original_string": "private GraphPanelChartAverageElement avgRespLatency = new GraphPanelChartAverageElement();", "modifier": "private", "type": "GraphPanelChartAverageElement", "declarator": "avgRespLatency = new GraphPanelChartAverageElement()", "var_name": "avgRespLatency"}, {"original_string": "private GraphPanelChartAverageElement errorRate = new GraphPanelChartAverageElement();", "modifier": "private", "type": "GraphPanelChartAverageElement", "declarator": "errorRate = new GraphPanelChartAverageElement()", "var_name": "errorRate"}, {"original_string": "private long respTimeExceededStart = 0;", "modifier": "private", "type": "long", "declarator": "respTimeExceededStart = 0", "var_name": "respTimeExceededStart"}, {"original_string": "private long errRateExceededStart = 0;", "modifier": "private", "type": "long", "declarator": "errRateExceededStart = 0", "var_name": "errRateExceededStart"}, {"original_string": "private long respLatencyExceededStart = 0;", "modifier": "private", "type": "long", "declarator": "respLatencyExceededStart = 0", "var_name": "respLatencyExceededStart"}, {"original_string": "private int stopTries = 0;", "modifier": "private", "type": "int", "declarator": "stopTries = 0", "var_name": "stopTries"}, {"original_string": "private int testValueRespTime = 0;", "modifier": "private", "type": "int", "declarator": "testValueRespTime = 0", "var_name": "testValueRespTime"}, {"original_string": "private int testValueRespTimeSec = 0;", "modifier": "private", "type": "int", "declarator": "testValueRespTimeSec = 0", "var_name": "testValueRespTimeSec"}, {"original_string": "private int testValueRespLatency = 0;", "modifier": "private", "type": "int", "declarator": "testValueRespLatency = 0", "var_name": "testValueRespLatency"}, {"original_string": "private int testValueRespLatencySec = 0;", "modifier": "private", "type": "int", "declarator": "testValueRespLatencySec = 0", "var_name": "testValueRespLatencySec"}, {"original_string": "private float testValueError = 0;", "modifier": "private", "type": "float", "declarator": "testValueError = 0", "var_name": "testValueError"}, {"original_string": "private int testValueErrorSec = 0;", "modifier": "private", "type": "int", "declarator": "testValueErrorSec = 0", "var_name": "testValueErrorSec"}], "methods": [{"identifier": "AutoStop", "parameters": "()", "modifiers": "public", "return": "", "signature": " AutoStop()", "full_signature": "public  AutoStop()", "class_method_signature": "AutoStop.AutoStop()", "testcase": false, "constructor": true}, {"identifier": "sampleOccurred", "parameters": "(SampleEvent se)", "modifiers": "@Override public", "return": "void", "signature": "void sampleOccurred(SampleEvent se)", "full_signature": "@Override public void sampleOccurred(SampleEvent se)", "class_method_signature": "AutoStop.sampleOccurred(SampleEvent se)", "testcase": false, "constructor": false}, {"identifier": "sampleStarted", "parameters": "(SampleEvent se)", "modifiers": "@Override public", "return": "void", "signature": "void sampleStarted(SampleEvent se)", "full_signature": "@Override public void sampleStarted(SampleEvent se)", "class_method_signature": "AutoStop.sampleStarted(SampleEvent se)", "testcase": false, "constructor": false}, {"identifier": "sampleStopped", "parameters": "(SampleEvent se)", "modifiers": "@Override public", "return": "void", "signature": "void sampleStopped(SampleEvent se)", "full_signature": "@Override public void sampleStopped(SampleEvent se)", "class_method_signature": "AutoStop.sampleStopped(SampleEvent se)", "testcase": false, "constructor": false}, {"identifier": "testStarted", "parameters": "()", "modifiers": "@Override public", "return": "void", "signature": "void testStarted()", "full_signature": "@Override public void testStarted()", "class_method_signature": "AutoStop.testStarted()", "testcase": false, "constructor": false}, {"identifier": "testStarted", "parameters": "(String string)", "modifiers": "@Override public", "return": "void", "signature": "void testStarted(String string)", "full_signature": "@Override public void testStarted(String string)", "class_method_signature": "AutoStop.testStarted(String string)", "testcase": false, "constructor": false}, {"identifier": "testEnded", "parameters": "()", "modifiers": "@Override public", "return": "void", "signature": "void testEnded()", "full_signature": "@Override public void testEnded()", "class_method_signature": "AutoStop.testEnded()", "testcase": false, "constructor": false}, {"identifier": "testEnded", "parameters": "(String string)", "modifiers": "@Override public", "return": "void", "signature": "void testEnded(String string)", "full_signature": "@Override public void testEnded(String string)", "class_method_signature": "AutoStop.testEnded(String string)", "testcase": false, "constructor": false}, {"identifier": "setResponseTime", "parameters": "(String text)", "modifiers": "", "return": "void", "signature": "void setResponseTime(String text)", "full_signature": " void setResponseTime(String text)", "class_method_signature": "AutoStop.setResponseTime(String text)", "testcase": false, "constructor": false}, {"identifier": "setResponseLatency", "parameters": "(String text)", "modifiers": "", "return": "void", "signature": "void setResponseLatency(String text)", "full_signature": " void setResponseLatency(String text)", "class_method_signature": "AutoStop.setResponseLatency(String text)", "testcase": false, "constructor": false}, {"identifier": "setErrorRate", "parameters": "(String text)", "modifiers": "", "return": "void", "signature": "void setErrorRate(String text)", "full_signature": " void setErrorRate(String text)", "class_method_signature": "AutoStop.setErrorRate(String text)", "testcase": false, "constructor": false}, {"identifier": "setResponseTimeSecs", "parameters": "(String text)", "modifiers": "", "return": "void", "signature": "void setResponseTimeSecs(String text)", "full_signature": " void setResponseTimeSecs(String text)", "class_method_signature": "AutoStop.setResponseTimeSecs(String text)", "testcase": false, "constructor": false}, {"identifier": "setResponseLatencySecs", "parameters": "(String text)", "modifiers": "", "return": "void", "signature": "void setResponseLatencySecs(String text)", "full_signature": " void setResponseLatencySecs(String text)", "class_method_signature": "AutoStop.setResponseLatencySecs(String text)", "testcase": false, "constructor": false}, {"identifier": "setErrorRateSecs", "parameters": "(String text)", "modifiers": "", "return": "void", "signature": "void setErrorRateSecs(String text)", "full_signature": " void setErrorRateSecs(String text)", "class_method_signature": "AutoStop.setErrorRateSecs(String text)", "testcase": false, "constructor": false}, {"identifier": "getResponseTime", "parameters": "()", "modifiers": "", "return": "String", "signature": "String getResponseTime()", "full_signature": " String getResponseTime()", "class_method_signature": "AutoStop.getResponseTime()", "testcase": false, "constructor": false}, {"identifier": "getResponseTimeSecs", "parameters": "()", "modifiers": "", "return": "String", "signature": "String getResponseTimeSecs()", "full_signature": " String getResponseTimeSecs()", "class_method_signature": "AutoStop.getResponseTimeSecs()", "testcase": false, "constructor": false}, {"identifier": "getResponseLatency", "parameters": "()", "modifiers": "", "return": "String", "signature": "String getResponseLatency()", "full_signature": " String getResponseLatency()", "class_method_signature": "AutoStop.getResponseLatency()", "testcase": false, "constructor": false}, {"identifier": "getResponseLatencySecs", "parameters": "()", "modifiers": "", "return": "String", "signature": "String getResponseLatencySecs()", "full_signature": " String getResponseLatencySecs()", "class_method_signature": "AutoStop.getResponseLatencySecs()", "testcase": false, "constructor": false}, {"identifier": "getErrorRate", "parameters": "()", "modifiers": "", "return": "String", "signature": "String getErrorRate()", "full_signature": " String getErrorRate()", "class_method_signature": "AutoStop.getErrorRate()", "testcase": false, "constructor": false}, {"identifier": "getErrorRateSecs", "parameters": "()", "modifiers": "", "return": "String", "signature": "String getErrorRateSecs()", "full_signature": " String getErrorRateSecs()", "class_method_signature": "AutoStop.getErrorRateSecs()", "testcase": false, "constructor": false}, {"identifier": "getResponseTimeAsInt", "parameters": "()", "modifiers": "private", "return": "int", "signature": "int getResponseTimeAsInt()", "full_signature": "private int getResponseTimeAsInt()", "class_method_signature": "AutoStop.getResponseTimeAsInt()", "testcase": false, "constructor": false}, {"identifier": "getResponseTimeSecsAsInt", "parameters": "()", "modifiers": "private", "return": "int", "signature": "int getResponseTimeSecsAsInt()", "full_signature": "private int getResponseTimeSecsAsInt()", "class_method_signature": "AutoStop.getResponseTimeSecsAsInt()", "testcase": false, "constructor": false}, {"identifier": "getResponseLatencyAsInt", "parameters": "()", "modifiers": "private", "return": "int", "signature": "int getResponseLatencyAsInt()", "full_signature": "private int getResponseLatencyAsInt()", "class_method_signature": "AutoStop.getResponseLatencyAsInt()", "testcase": false, "constructor": false}, {"identifier": "getResponseLatencySecsAsInt", "parameters": "()", "modifiers": "private", "return": "int", "signature": "int getResponseLatencySecsAsInt()", "full_signature": "private int getResponseLatencySecsAsInt()", "class_method_signature": "AutoStop.getResponseLatencySecsAsInt()", "testcase": false, "constructor": false}, {"identifier": "getErrorRateAsFloat", "parameters": "()", "modifiers": "private", "return": "float", "signature": "float getErrorRateAsFloat()", "full_signature": "private float getErrorRateAsFloat()", "class_method_signature": "AutoStop.getErrorRateAsFloat()", "testcase": false, "constructor": false}, {"identifier": "getErrorRateSecsAsInt", "parameters": "()", "modifiers": "private", "return": "int", "signature": "int getErrorRateSecsAsInt()", "full_signature": "private int getErrorRateSecsAsInt()", "class_method_signature": "AutoStop.getErrorRateSecsAsInt()", "testcase": false, "constructor": false}, {"identifier": "stopTest", "parameters": "()", "modifiers": "private", "return": "void", "signature": "void stopTest()", "full_signature": "private void stopTest()", "class_method_signature": "AutoStop.stopTest()", "testcase": false, "constructor": false}, {"identifier": "stopTestViaUDP", "parameters": "(String command)", "modifiers": "private", "return": "void", "signature": "void stopTestViaUDP(String command)", "full_signature": "private void stopTestViaUDP(String command)", "class_method_signature": "AutoStop.stopTestViaUDP(String command)", "testcase": false, "constructor": false}], "file": "plugins/autostop/src/main/java/kg/apc/jmeter/reporters/AutoStop.java"}, "focal_method": {"identifier": "setErrorRate", "parameters": "(String text)", "modifiers": "", "return": "void", "body": "void setErrorRate(String text) {\n        setProperty(ERROR_RATE, text);\n    }", "signature": "void setErrorRate(String text)", "full_signature": " void setErrorRate(String text)", "class_method_signature": "AutoStop.setErrorRate(String text)", "testcase": false, "constructor": false, "invocations": ["setProperty"]}, "repository": {"repo_id": 8197357, "url": "https://github.com/undera/jmeter-plugins", "stars": 388, "created": "2/14/2013 10:17:40 AM +00:00", "updates": "2020-01-26T06:36:21+00:00", "fork": "False", "license": "licensed"}}