{"test_class": {"identifier": "PODRepositoryTest", "superclass": "", "interfaces": "", "fields": [{"original_string": "@Mock\n  PODMapper mapper;", "modifier": "@Mock", "type": "PODMapper", "declarator": "mapper", "var_name": "mapper"}, {"original_string": "@InjectMocks\n  PODRepository repository;", "modifier": "@InjectMocks", "type": "PODRepository", "declarator": "repository", "var_name": "repository"}], "file": "modules/shipment/src/test/java/org/openlmis/pod/repository/PODRepositoryTest.java"}, "test_case": {"identifier": "shouldInsertPOD", "parameters": "()", "modifiers": "@Test public", "return": "void", "body": "@Test\n  public void shouldInsertPOD() {\n    OrderPOD orderPod = new OrderPOD();\n    repository.insertPOD(orderPod);\n    verify(mapper).insertPOD(orderPod);\n  }", "signature": "void shouldInsertPOD()", "full_signature": "@Test public void shouldInsertPOD()", "class_method_signature": "PODRepositoryTest.shouldInsertPOD()", "testcase": true, "constructor": false, "invocations": ["insertPOD", "insertPOD", "verify"]}, "focal_class": {"identifier": "PODRepository", "superclass": "", "interfaces": "", "fields": [{"original_string": "@Autowired\n  PODMapper mapper;", "modifier": "@Autowired", "type": "PODMapper", "declarator": "mapper", "var_name": "mapper"}], "methods": [{"identifier": "insertPODLineItem", "parameters": "(OrderPODLineItem orderPodLineItem)", "modifiers": "public", "return": "void", "signature": "void insertPODLineItem(OrderPODLineItem orderPodLineItem)", "full_signature": "public void insertPODLineItem(OrderPODLineItem orderPodLineItem)", "class_method_signature": "PODRepository.insertPODLineItem(OrderPODLineItem orderPodLineItem)", "testcase": false, "constructor": false}, {"identifier": "insertPOD", "parameters": "(OrderPOD orderPod)", "modifiers": "public", "return": "void", "signature": "void insertPOD(OrderPOD orderPod)", "full_signature": "public void insertPOD(OrderPOD orderPod)", "class_method_signature": "PODRepository.insertPOD(OrderPOD orderPod)", "testcase": false, "constructor": false}, {"identifier": "getPODByOrderId", "parameters": "(Long orderId)", "modifiers": "public", "return": "OrderPOD", "signature": "OrderPOD getPODByOrderId(Long orderId)", "full_signature": "public OrderPOD getPODByOrderId(Long orderId)", "class_method_signature": "PODRepository.getPODByOrderId(Long orderId)", "testcase": false, "constructor": false}, {"identifier": "getNPodLineItems", "parameters": "(String productCode, Rnr requisition, Integer n, Date startDate)", "modifiers": "public", "return": "List<OrderPODLineItem>", "signature": "List<OrderPODLineItem> getNPodLineItems(String productCode, Rnr requisition, Integer n, Date startDate)", "full_signature": "public List<OrderPODLineItem> getNPodLineItems(String productCode, Rnr requisition, Integer n, Date startDate)", "class_method_signature": "PODRepository.getNPodLineItems(String productCode, Rnr requisition, Integer n, Date startDate)", "testcase": false, "constructor": false}, {"identifier": "getPOD", "parameters": "(Long podId)", "modifiers": "public", "return": "OrderPOD", "signature": "OrderPOD getPOD(Long podId)", "full_signature": "public OrderPOD getPOD(Long podId)", "class_method_signature": "PODRepository.getPOD(Long podId)", "testcase": false, "constructor": false}, {"identifier": "insert", "parameters": "(OrderPOD orderPOD)", "modifiers": "public", "return": "OrderPOD", "signature": "OrderPOD insert(OrderPOD orderPOD)", "full_signature": "public OrderPOD insert(OrderPOD orderPOD)", "class_method_signature": "PODRepository.insert(OrderPOD orderPOD)", "testcase": false, "constructor": false}, {"identifier": "update", "parameters": "(OrderPOD orderPOD)", "modifiers": "public", "return": "OrderPOD", "signature": "OrderPOD update(OrderPOD orderPOD)", "full_signature": "public OrderPOD update(OrderPOD orderPOD)", "class_method_signature": "PODRepository.update(OrderPOD orderPOD)", "testcase": false, "constructor": false}], "file": "modules/shipment/src/main/java/org/openlmis/pod/repository/PODRepository.java"}, "focal_method": {"identifier": "insertPOD", "parameters": "(OrderPOD orderPod)", "modifiers": "public", "return": "void", "body": "public void insertPOD(OrderPOD orderPod) {\n    mapper.insertPOD(orderPod);\n  }", "signature": "void insertPOD(OrderPOD orderPod)", "full_signature": "public void insertPOD(OrderPOD orderPod)", "class_method_signature": "PODRepository.insertPOD(OrderPOD orderPod)", "testcase": false, "constructor": false, "invocations": ["insertPOD"]}, "repository": {"repo_id": 6172406, "url": "https://github.com/OpenLMIS/open-lmis", "language": "Java", "is_fork": false, "fork_count": 54, "stargazer_count": 89, "size": 125128, "license": "licensed"}}